setup.py
dsdn_distrib_20230330_gk/Binomialdistribution.py
dsdn_distrib_20230330_gk/Gaussiandistribution.py
dsdn_distrib_20230330_gk/Generaldistribution.py
dsdn_distrib_20230330_gk/__init__.py
dsdn_distrib_20230330_gk.egg-info/PKG-INFO
dsdn_distrib_20230330_gk.egg-info/SOURCES.txt
dsdn_distrib_20230330_gk.egg-info/dependency_links.txt
dsdn_distrib_20230330_gk.egg-info/not-zip-safe
dsdn_distrib_20230330_gk.egg-info/top_level.txt