Metadata-Version: 1.0
Name: dsdn-distrib-20230330-gk
Version: 0.1
Summary: Gaussian and binomial distribution
Home-page: UNKNOWN
Author: Georgios Kokkinopoulos
Author-email: georgioskokkinopoulos@gmail.com
License: UNKNOWN
Platform: UNKNOWN
